README.rst
setup.py
blackwidow/__init__.py
blackwidow/config.py
blackwidow/error.py
blackwidow/imports.py
blackwidow/node.py
blackwidow/web.py
blackwidow.egg-info/PKG-INFO
blackwidow.egg-info/SOURCES.txt
blackwidow.egg-info/dependency_links.txt
blackwidow.egg-info/requires.txt
blackwidow.egg-info/top_level.txt
blackwidow/tests/__init__.py
blackwidow/tests/test_error.py
blackwidow/viz/__init__.py
blackwidow/viz/server.py
blackwidow/viz/static/graph.css
blackwidow/viz/static/graph.html
blackwidow/viz/static/graph.js
blackwidow/viz/static/graph.json