Metadata-Version: 1.0
Name: blackwidow
Version: 0.1.5
Summary: 
Home-page: https://github.com/madisonmay/blackwidow
Author: Madison May
Author-email: madison@indico.io
License: MIT License (See LICENSE)
Platform: UNKNOWN
